Metadata-Version: 1.1
Name: datafy
Version: 0.1.0
Summary: Read download URLs into datasets.
Home-page: https://github.com/ResidentMario/datafy
Author: Aleksey Bilogur
Author-email: aleksey.bilogur@gmail.com
License: UNKNOWN
Download-URL: https://github.com/ResidentMario/datafy/tarball/0.1.0
Keywords: data,requests,data analysis,geospatial data,geospatial analytics,pandas
Platform: UNKNOWN
